pydish/__init__.py
pydish/connector.py
pydish/device_server.py
pydish/http_server.py
pydish/static/__init__.py
pydish/static/connector.js
pydish/static/device.html
pydish/static/display_firmware.js
pydish-0.102.dist-info/LICENSE
pydish-0.102.dist-info/METADATA
pydish-0.102.dist-info/WHEEL
pydish-0.102.dist-info/top_level.txt
pydish-0.102.dist-info/RECORD
